tests/__init__.py
tests/test_generate_wallet.py
vanitycosmos/__init__.py
vanitycosmos/__main__.py
vanitycosmos/vanitycosmos.py
vanity_cosmos-0.1.0.dist-info/LICENSE
vanity_cosmos-0.1.0.dist-info/METADATA
vanity_cosmos-0.1.0.dist-info/WHEEL
vanity_cosmos-0.1.0.dist-info/entry_points.txt
vanity_cosmos-0.1.0.dist-info/top_level.txt
vanity_cosmos-0.1.0.dist-info/RECORD
