Metadata-Version: 2.1
Name: vanity-cosmos
Version: 0.1.0
Summary: Tool for generating custom cosmos addresses.
Home-page: https://github.com/etimoz/vanity-cosmos/
Author: Paul Angerer
Author-email: etimoz@users.noreply.github.com
License: UNKNOWN
Keywords: cosmos blockchain atom cryptocurrency address generator vanity
Platform: UNKNOWN
Classifier: Programming Language :: Python :: 3
Classifier: License :: OSI Approved :: MIT License
Classifier: Operating System :: OS Independent
Requires-Python: >=3.6
Requires-Dist: bech32
Requires-Dist: secp256k1
Provides-Extra: test
Requires-Dist: pytest ; extra == 'test'
Requires-Dist: pytest-cov ; extra == 'test'
Requires-Dist: pytest-mock ; extra == 'test'
Requires-Dist: bech32 ; extra == 'test'
Requires-Dist: secp256k1 ; extra == 'test'
